tablate/__init__.py
tablate/api/Tablate.py
tablate/api/__init__.py
tablate/api/functions/__init__.py
tablate/api/functions/concat.py
tablate/api/modules/Grid.py
tablate/api/modules/Table.py
tablate/api/modules/Text.py
tablate/api/modules/__init__.py
tablate/classes/__init__.py
tablate/classes/classes.py
tablate/classes/bases/TablateApiBase.py
tablate/classes/bases/TablateApiItem.py
tablate/classes/bases/TablateApiSet.py
tablate/classes/bases/TablateBase.py
tablate/classes/bases/TablateItem.py
tablate/classes/bases/TablateSet.py
tablate/classes/bases/__init__.py
tablate/classes/helpers/__init__.py
tablate/classes/helpers/get_frame.py
tablate/classes/helpers/list_frame.py
tablate/classes/helpers/remove_frame.py
tablate/classes/helpers/replace_frame.py
tablate/classes/helpers/select_frame.py
tablate/classes/options/__init__.py
tablate/classes/options/html/__init__.py
tablate/classes/options/html/style/CssStyler.py
tablate/classes/options/html/style/__init__.py
tablate/classes/options/html/style/mixins/AddStyleMixin.py
tablate/classes/options/html/style/mixins/ClassNameMixin.py
tablate/classes/options/html/style/mixins/__init__.py
tablate/classes/options/html/style/subclasses/ElementStyler.py
tablate/classes/options/html/style/subclasses/TableStyler.py
tablate/classes/options/html/style/subclasses/TextStyler.py
tablate/classes/options/html/style/subclasses/__init__.py
tablate/classes/options/html/style/utilities/__init__.py
tablate/classes/options/html/style/utilities/base_values.py
tablate/classes/options/html/style/utilities/css_factory.py
tablate/classes/options/html/style/utilities/selectors.py
tablate/classes/options/html/style/utilities/style_dict.py
tablate/classes/options/html/style/utilities/style_types.py
tablate/library/__init__.py
tablate/library/ascii/__init__.py
tablate/library/ascii/chars/__init__.py
tablate/library/ascii/chars/corners.py
tablate/library/ascii/chars/line_h.py
tablate/library/ascii/chars/line_v.py
tablate-0.1.12.dist-info/LICENCE
tablate-0.1.12.dist-info/METADATA
tablate-0.1.12.dist-info/WHEEL
tablate-0.1.12.dist-info/top_level.txt
tablate-0.1.12.dist-info/RECORD
